WebScraperX/__init__.py
WebScraperX/fetcher.py
webscraperx-0.1.dist-info/METADATA
webscraperx-0.1.dist-info/WHEEL
webscraperx-0.1.dist-info/top_level.txt
webscraperx-0.1.dist-info/RECORD
