Metadata-Version: 2.4
Name: WebScraperX
Version: 0.1
Summary: Bir web sitesini alir ve HTML yapisini Python objesi olarak dondurur.
Home-page: https://github.com/ruzgar/WebScraperX
Author: Ruzgar
Classifier: Programming Language :: Python :: 3
Classifier: Operating System :: OS Independent
Classifier: Topic :: Internet :: WWW/HTTP
Requires-Python: >=3.6
Requires-Dist: requests
Requires-Dist: beautifulsoup4
Dynamic: author
Dynamic: classifier
Dynamic: description
Dynamic: description-content-type
Dynamic: home-page
Dynamic: requires-dist
Dynamic: requires-python
Dynamic: summary
